TGFaceRecognition/__init__.py
TGFaceRecognition/faceRecognitionFromCameraLL - ÉRÉsÅ[.py
TGFaceRecognition-0.0.3.dist-info/DESCRIPTION.rst
TGFaceRecognition-0.0.3.dist-info/METADATA
TGFaceRecognition-0.0.3.dist-info/RECORD
TGFaceRecognition-0.0.3.dist-info/WHEEL
TGFaceRecognition-0.0.3.dist-info/metadata.json
TGFaceRecognition-0.0.3.dist-info/top_level.txt
